ev3sim/__init__.py
ev3sim/__main__.py
ev3sim/attach_bot.py
ev3sim/batched_run.py
ev3sim/code_helpers.py
ev3sim/constants.py
ev3sim/entry.py
ev3sim/events.py
ev3sim/file_helper.py
ev3sim/logging.py
ev3sim/robot.py
ev3sim/search_locations.py
ev3sim/settings.py
ev3sim/sim.py
ev3sim/updates.py
ev3sim/utils.py
ev3sim/assets/Logo.bmp
ev3sim/assets/Logo.ico
ev3sim/assets/Logo.png
ev3sim/assets/__init__.py
ev3sim/assets/bg_slide0.png
ev3sim/assets/bg_slide1.png
ev3sim/assets/bg_slide2.png
ev3sim/assets/bg_slide3.png
ev3sim/assets/default_theme.json
ev3sim/assets/installer_preview.bmp
ev3sim/assets/rescue_bg.png
ev3sim/assets/rescue_preview.png
ev3sim/assets/soccer_bg.png
ev3sim/assets/soccer_preview.png
ev3sim/assets/fonts/OFL.txt
ev3sim/assets/fonts/OpenSans-SemiBold.ttf
ev3sim/assets/fonts/OpenSans.ttf
ev3sim/assets/fonts/Poppins-Black.ttf
ev3sim/assets/fonts/Poppins-BlackItalic.ttf
ev3sim/assets/fonts/Poppins-Bold.ttf
ev3sim/assets/fonts/Poppins-BoldItalic.ttf
ev3sim/assets/fonts/Poppins-ExtraBold.ttf
ev3sim/assets/fonts/Poppins-ExtraBoldItalic.ttf
ev3sim/assets/fonts/Poppins-ExtraLight.ttf
ev3sim/assets/fonts/Poppins-ExtraLightItalic.ttf
ev3sim/assets/fonts/Poppins-Italic.ttf
ev3sim/assets/fonts/Poppins-Light.ttf
ev3sim/assets/fonts/Poppins-LightItalic.ttf
ev3sim/assets/fonts/Poppins-Medium.ttf
ev3sim/assets/fonts/Poppins-MediumItalic.ttf
ev3sim/assets/fonts/Poppins-Regular.ttf
ev3sim/assets/fonts/Poppins-SemiBold.ttf
ev3sim/assets/fonts/Poppins-SemiBoldItalic.ttf
ev3sim/assets/fonts/Poppins-Thin.ttf
ev3sim/assets/fonts/Poppins-ThinItalic.ttf
ev3sim/assets/fonts/Roboto-Bold.ttf
ev3sim/assets/fonts/Roboto-BoldItalic.ttf
ev3sim/assets/fonts/Roboto-Italic.ttf
ev3sim/assets/fonts/Roboto-Regular.ttf
ev3sim/assets/fonts/__init__.py
ev3sim/assets/ui/add.png
ev3sim/assets/ui/bin.png
ev3sim/assets/ui/bot.png
ev3sim/assets/ui/box_check.png
ev3sim/assets/ui/box_clear.png
ev3sim/assets/ui/button_fg.png
ev3sim/assets/ui/code.png
ev3sim/assets/ui/controls_pause_hold.png
ev3sim-2.2.3.dist-info/LICENSE
ev3sim-2.2.3.dist-info/METADATA
ev3sim-2.2.3.dist-info/WHEEL
ev3sim-2.2.3.dist-info/entry_points.txt
ev3sim-2.2.3.dist-info/top_level.txt
ev3sim-2.2.3.dist-info/RECORD
