Metadata-Version: 2.1
Name: ev3sim
Version: 2.2.3
Summary: Simulate ev3dev programs in Python
Home-page: https://github.com/MelbourneHighSchoolRobotics/ev3sim
Author: Jackson Goerner, James Bui, Richard Huang, Angus Trau, Peter Drew
Author-email: jgoerner@outlook.com, jtbui20@gmail.com, me@huangrichard.com, contact@angus.ws, peter@pdrew.com
License: BSD-3-Clause
Platform: UNKNOWN
Classifier: License :: OSI Approved :: BSD License
Classifier: Development Status :: 4 - Beta
Classifier: Programming Language :: Python
Classifier: Programming Language :: Python :: 3
Classifier: Framework :: Robot Framework
Classifier: Framework :: Robot Framework :: Tool
Classifier: Topic :: Software Development :: Libraries :: pygame
Classifier: Topic :: Software Development :: Testing :: Mocking
Requires-Python: >=3.9.0
License-File: LICENSE
Requires-Dist: numpy (==1.19.3)
Requires-Dist: pygame (==2.0.1)
Requires-Dist: PyYAML (==5.4)
Requires-Dist: pymunk (==6.0.0)
Requires-Dist: python-ev3dev2 (==2.1.0.post1)
Requires-Dist: opensimplex (==0.3)
Requires-Dist: pygame-gui (==0.5.7)
Requires-Dist: sentry-sdk (==0.20.0)
Requires-Dist: debugpy (==1.2.1)
Requires-Dist: python-certifi-win32 (==1.6)
Requires-Dist: mindpile (==0.0.2)
Requires-Dist: requests (==2.25.1)
